MANIFEST.in
setup.py
JarbasModelZoo/__init__.py
JarbasModelZoo.egg-info/PKG-INFO
JarbasModelZoo.egg-info/SOURCES.txt
JarbasModelZoo.egg-info/dependency_links.txt
JarbasModelZoo.egg-info/top_level.txt
JarbasModelZoo/features/__init__.py
JarbasModelZoo/nltk_chunkers/__init__.py
JarbasModelZoo/nltk_taggers/__init__.py
JarbasModelZoo/res/nltk_brown_brill_tagger.json
JarbasModelZoo/res/nltk_brown_maxent_tagger.json
JarbasModelZoo/res/nltk_brown_ngram_tagger.json
JarbasModelZoo/res/nltk_cess_cat_brill_tagger.json
JarbasModelZoo/res/nltk_cess_cat_udep_brill_tagger.json
JarbasModelZoo/res/nltk_cess_cat_udep_ngram_tagger.json
JarbasModelZoo/res/nltk_cess_esp_brill_tagger.json
JarbasModelZoo/res/nltk_cess_esp_udep_brill_tagger.json
JarbasModelZoo/res/nltk_cess_esp_udep_ngram_tagger.json
JarbasModelZoo/res/nltk_clftagger_WNUT17_NER.json
JarbasModelZoo/res/nltk_clftagger_conll2003_NER.json
JarbasModelZoo/res/nltk_clftagger_gmb_NER.json
JarbasModelZoo/res/nltk_clftagger_leNERbr_NER.json
JarbasModelZoo/res/nltk_clftagger_onto5_NER.json
JarbasModelZoo/res/nltk_clftagger_paramopama+harem_NER.json
JarbasModelZoo/res/nltk_clftagger_paramopama_NER.json
JarbasModelZoo/res/nltk_clftagger_slsmovies_NER.json
JarbasModelZoo/res/nltk_clftagger_slsrestaurants_NER.json
JarbasModelZoo/res/nltk_clftagger_slstrivia10k13_NER.json
JarbasModelZoo/res/nltk_conll2000_clf_chunk_tagger.json
JarbasModelZoo/res/nltk_conll2000_clf_chunker.json
JarbasModelZoo/res/nltk_conll2000_postag_ngram_chunk_tagger.json
JarbasModelZoo/res/nltk_conll2000_postag_ngram_chunker.json
JarbasModelZoo/res/nltk_dtree_gender_clf.json
JarbasModelZoo/res/nltk_floresta_brill_tagger.json
JarbasModelZoo/res/nltk_floresta_macmorpho_brill_tagger.json
JarbasModelZoo/res/nltk_floresta_ngram_tagger.json
JarbasModelZoo/res/nltk_macmorpho_brill_tagger.json
JarbasModelZoo/res/nltk_macmorpho_udep_brill_tagger.json
JarbasModelZoo/res/nltk_macmorpho_udep_ngram_tagger.json
JarbasModelZoo/res/nltk_maxent_gender_clf.json
JarbasModelZoo/res/nltk_nb_gender_clf.json
JarbasModelZoo/res/nltk_nilc_brill_tagger.json
JarbasModelZoo/res/nltk_nilc_ngram_tagger.json
