Metadata-Version: 2.1
Name: JarbasModelZoo
Version: 0.2.0a2.post1
Summary: pretrained models (down)loader
Home-page: https://github.com/OpenJarbas/ModelZoo
Author: jarbasai
Author-email: jarbasai@mailfence.com
License: apache-2.0
Platform: UNKNOWN
